LICENSE
MANIFEST.in
README.md
setup.py
sentry_redflash/__init__.py
sentry_redflash/__init__.pyc
sentry_redflash/client.py
sentry_redflash/client.pyc
sentry_redflash/plugin.py
sentry_redflash/plugin.pyc
sentry_redflash.egg-info/PKG-INFO
sentry_redflash.egg-info/SOURCES.txt
sentry_redflash.egg-info/dependency_links.txt
sentry_redflash.egg-info/entry_points.txt
sentry_redflash.egg-info/not-zip-safe
sentry_redflash.egg-info/requires.txt
sentry_redflash.egg-info/top_level.txt