Metadata-Version: 1.0
Name: sentry-redflash
Version: 0.0.8
Summary: A Sentry extension which integrates with Redflash.
Home-page: http://github.com/davidszotten/sentry-redflash
Author: David Szotten
Author-email: Author name (as one word) at gmail.com
License: MIT
Platform: UNKNOWN
